[
    {
        "name": "Tatooine",
        "rotation_period": "23",
        "orbital_period": "304",
        "diameter": "10465",
        "climate": "arid",
        "gravity": "1 standard",
        "terrain": "desert",
        "surface_water": "1",
        "population": "200000",
        "created": "2014-12-09T13:50:49.641000Z",
        "edited": "2014-12-21T20:48:04.175778Z",
        "url": "https://swapi.co/api/planets/1/"
    },
    {
        "name": "Alderaan",
        "rotation_period": "24",
        "orbital_period": "364",
        "diameter": "12500",
        "climate": "temperate",
        "gravity": "1 standard",
        "terrain": "grasslands, mountains",
        "surface_water": "40",
        "population": "2000000000",
        "created": "2014-12-10T11:35:48.479000Z",
        "edited": "2014-12-20T20:58:18.420000Z",
        "url": "https://swapi.co/api/planets/2/"
    },
    {
        "name": "Bespin",
        "rotation_period": "12",
        "orbital_period": "5110",
        "diameter": "118000",
        "climate": "temperate",
        "gravity": "1.5 (surface), 1 standard (Cloud City)",
        "terrain": "gas giant",
        "surface_water": "0",
        "population": "6000000",
        "created": "2014-12-10T11:43:55.240000Z",
        "edited": "2014-12-20T20:58:18.427000Z",
        "url": "https://swapi.co/api/planets/6/"
    },
    {
        "name": "Naboo",
        "rotation_period": "26",
        "orbital_period": "312",
        "diameter": "12120",
        "climate": "temperate",
        "gravity": "1 standard",
        "terrain": "grassy hills, swamps, forests, mountains",
        "surface_water": "12",
        "population": "4500000000",
        "created": "2014-12-10T11:52:31.066000Z",
        "edited": "2014-12-20T20:58:18.430000Z",
        "url": "https://swapi.co/api/planets/8/"
    },
    {
        "name": "Kamino",
        "rotation_period": "27",
        "orbital_period": "463",
        "diameter": "19720",
        "climate": "temperate",
        "gravity": "1 standard",
        "terrain": "ocean",
        "surface_water": "100",
        "population": "1000000000",
        "created": "2014-12-10T12:45:06.577000Z",
        "edited": "2014-12-20T20:58:18.434000Z",
        "url": "https://swapi.co/api/planets/10/"
    },
    {
        "name": "Kashyyyk",
        "rotation_period": "26",
        "orbital_period": "381",
        "diameter": "12765",
        "climate": "tropical",
        "gravity": "1 standard",
        "terrain": "jungle, forests, lakes, rivers",
        "surface_water": "60",
        "population": "45000000",
        "created": "2014-12-10T13:32:00.124000Z",
        "edited": "2014-12-20T20:58:18.442000Z",
        "url": "https://swapi.co/api/planets/14/"
    },
    {
        "name": "Stewjon",
        "diameter": "0",
        "climate": "temperate",
        "gravity": "1 standard",
        "terrain": "grass",
        "created": "2014-12-10T16:16:26.566000Z",
        "edited": "2014-12-20T20:58:18.452000Z",
        "url": "https://swapi.co/api/planets/20/"
    },
    {
        "name": "Eriadu",
        "rotation_period": "24",
        "orbital_period": "360",
        "diameter": "13490",
        "climate": "polluted",
        "gravity": "1 standard",
        "terrain": "cityscape",
        "population": "22000000000",
        "created": "2014-12-10T16:26:54.384000Z",
        "edited": "2014-12-20T20:58:18.454000Z",
        "url": "https://swapi.co/api/planets/21/"
    },
    {
        "name": "Corellia",
        "rotation_period": "25",
        "orbital_period": "329",
        "diameter": "11000",
        "climate": "temperate",
        "gravity": "1 standard",
        "terrain": "plains, urban, hills, forests",
        "surface_water": "70",
        "population": "3000000000",
        "created": "2014-12-10T16:49:12.453000Z",
        "edited": "2014-12-20T20:58:18.456000Z",
        "url": "https://swapi.co/api/planets/22/"
    },
    {
        "name": "Nal Hutta",
        "rotation_period": "87",
        "orbital_period": "413",
        "diameter": "12150",
        "climate": "temperate",
        "gravity": "1 standard",
        "terrain": "urban, oceans, swamps, bogs",
        "population": "7000000000",
        "created": "2014-12-10T17:11:29.452000Z",
        "edited": "2014-12-20T20:58:18.460000Z",
        "url": "https://swapi.co/api/planets/24/"
    },
    {
        "name": "Bestine IV",
        "rotation_period": "26",
        "orbital_period": "680",
        "diameter": "6400",
        "climate": "temperate",
        "terrain": "rocky islands, oceans",
        "surface_water": "98",
        "population": "62000000",
        "created": "2014-12-12T11:16:55.078000Z",
        "edited": "2014-12-20T20:58:18.463000Z",
        "url": "https://swapi.co/api/planets/26/"
    },
    {
        "name": "Trandosha",
        "rotation_period": "25",
        "orbital_period": "371",
        "diameter": "0",
        "climate": "arid",
        "gravity": "0.62 standard",
        "terrain": "mountains, seas, grasslands, deserts",
        "population": "42000000",
        "created": "2014-12-15T12:53:47.695000Z",
        "edited": "2014-12-20T20:58:18.468000Z",
        "url": "https://swapi.co/api/planets/29/"
    },
    {
        "name": "Socorro",
        "rotation_period": "20",
        "orbital_period": "326",
        "diameter": "0",
        "climate": "arid",
        "gravity": "1 standard",
        "terrain": "deserts, mountains",
        "population": "300000000",
        "created": "2014-12-15T12:56:31.121000Z",
        "edited": "2014-12-20T20:58:18.469000Z",
        "url": "https://swapi.co/api/planets/30/"
    },
    {
        "name": "Mon Cala",
        "rotation_period": "21",
        "orbital_period": "398",
        "diameter": "11030",
        "climate": "temperate",
        "gravity": "1",
        "terrain": "oceans, reefs, islands",
        "surface_water": "100",
        "population": "27000000000",
        "created": "2014-12-18T11:07:01.792000Z",
        "edited": "2014-12-20T20:58:18.471000Z",
        "url": "https://swapi.co/api/planets/31/"
    },
    {
        "name": "Chandrila",
        "rotation_period": "20",
        "orbital_period": "368",
        "diameter": "13500",
        "climate": "temperate",
        "gravity": "1",
        "terrain": "plains, forests",
        "surface_water": "40",
        "population": "1200000000",
        "created": "2014-12-18T11:11:51.872000Z",
        "edited": "2014-12-20T20:58:18.472000Z",
        "url": "https://swapi.co/api/planets/32/"
    }
]